{
    "niv": {
        "branch": "master",
        "description": "Easy dependency management for Nix projects",
        "homepage": "https://github.com/nmattia/niv",
        "owner": "nmattia",
        "repo": "niv",
        "rev": "8b7b70465c130d8d7a98fba1396ad1481daee518",
        "sha256": "0fgdrxn2vzpnzr6pxaiyn5zzbd812c6f7xjjhfir0kpzamjnxwwl",
        "type": "tarball",
        "url": "https://github.com/nmattia/niv/archive/8b7b70465c130d8d7a98fba1396ad1481daee518.tar.gz",
        "url_template": "https://github.com/<owner>/<repo>/archive/<rev>.tar.gz"
    },
    "nixpkgs": {
        "branch": "nixos-unstable",
        "description": "Nixpkgs/NixOS branches that track the Nixpkgs/NixOS channels",
        "homepage": null,
        "owner": "NixOS",
        "repo": "nixpkgs-channels",
        "rev": "362be9608c3e0dc5216e9d1d5f5c1a5643b7f7b1",
        "sha256": "0934rhanamsnhawg15gg6cy9ird3c47hsqn5s46lq2n5kzl6v7ly",
        "type": "tarball",
        "url": "https://github.com/NixOS/nixpkgs-channels/archive/362be9608c3e0dc5216e9d1d5f5c1a5643b7f7b1.tar.gz",
        "url_template": "https://github.com/<owner>/<repo>/archive/<rev>.tar.gz"
    }
}
